string_funcs.cpython-36m-darwin.so
pandas_lite/__init__.py
pandas_lite/frame.py
pandas_lite/options.py
pandas_lite/utils.py
pandas_lite/_libs/StringClass.cpython-36m-darwin.so
pandas_lite/_libs/__init__.py
pandas_lite/_libs/groupby.cpython-36m-darwin.so
pandas_lite/_libs/math.cpython-36m-darwin.so
pandas_lite/_libs/stat_funcs.py
pandas_lite/_libs/string_funcs.cpython-36m-darwin.so
pandas_lite/_libs/validate_arrays.cpython-36m-darwin.so
pandas_lite/tests/__init__.py
pandas_lite/tests/test_frame.py
pandas_lite/tests/testing.py
pandas_lite-0.1.2.dist-info/DESCRIPTION.rst
pandas_lite-0.1.2.dist-info/METADATA
pandas_lite-0.1.2.dist-info/RECORD
pandas_lite-0.1.2.dist-info/WHEEL
pandas_lite-0.1.2.dist-info/metadata.json
pandas_lite-0.1.2.dist-info/top_level.txt
