Metadata-Version: 2.0
Name: pandas-lite
Version: 0.1.2
Summary: A lighter version of pandas. No Series, No hierarchical indexing, only one indexer [ ]
Home-page: https://github.com/tdpetrou/pandas_lite
Author: Ted Petrou
Author-email: petrou.theodore@gmail.com
License: BSD 3-clause
Keywords: data pandas aggregation
Platform: UNKNOWN
Classifier: Development Status :: 3 - Alpha
Classifier: Intended Audience :: Science/Research
Classifier: Topic :: Scientific/Engineering
Classifier: License :: OSI Approved :: BSD License
Classifier: Programming Language :: Python :: 3.6
Requires-Python: >=3.6
Requires-Dist: numpy
